common_hms_library/__init__.py
common_hms_library/age_calculation.py
common_hms_library-1.1.dist-info/METADATA
common_hms_library-1.1.dist-info/WHEEL
common_hms_library-1.1.dist-info/top_level.txt
common_hms_library-1.1.dist-info/RECORD
