Metadata-Version: 2.1
Name: common_hms_library
Version: 1.1
Summary: Library for calculating age as float based on date of birth
Author: Aditya Sharma
Author-email: aditya@softprimeconsulting.com
Classifier: Programming Language :: Python :: 3
Classifier: License :: OSI Approved :: MIT License
Classifier: Operating System :: OS Independent
